<?xml version="1.0" encoding="UTF-8" standalone="yes"?>
<template encoding-version="1.3">
    <description></description>
    <groupId>7ec511e5-0192-1000-c99b-5ef509e3e37a</groupId>
    <name>generate_table_json</name>
    <snippet>
        <connections>
            <id>28d84f5c-42aa-3bc1-0000-000000000000</id>
            <parentGroupId>0cbfb181-9bd8-34d2-0000-000000000000</parentGroupId>
            <backPressureDataSizeThreshold>1 GB</backPressureDataSizeThreshold>
            <backPressureObjectThreshold>10000</backPressureObjectThreshold>
            <bends>
                <x>1112.0</x>
                <y>384.0</y>
            </bends>
            <destination>
                <groupId>0cbfb181-9bd8-34d2-0000-000000000000</groupId>
                <id>0ae476de-c16b-393e-0000-000000000000</id>
                <type>PROCESSOR</type>
            </destination>
            <flowFileExpiration>0 sec</flowFileExpiration>
            <labelIndex>1</labelIndex>
            <loadBalanceCompression>DO_NOT_COMPRESS</loadBalanceCompression>
            <loadBalancePartitionAttribute></loadBalancePartitionAttribute>
            <loadBalanceStatus>LOAD_BALANCE_NOT_CONFIGURED</loadBalanceStatus>
            <loadBalanceStrategy>DO_NOT_LOAD_BALANCE</loadBalanceStrategy>
            <name></name>
            <selectedRelationships>success</selectedRelationships>
            <source>
                <groupId>0cbfb181-9bd8-34d2-0000-000000000000</groupId>
                <id>fee7dd4b-510b-3705-0000-000000000000</id>
                <type>PROCESSOR</type>
            </source>
            <zIndex>0</zIndex>
        </connections>
        <connections>
            <id>765d4e4e-2cfd-32f5-0000-000000000000</id>
            <parentGroupId>0cbfb181-9bd8-34d2-0000-000000000000</parentGroupId>
            <backPressureDataSizeThreshold>1 GB</backPressureDataSizeThreshold>
            <backPressureObjectThreshold>10000</backPressureObjectThreshold>
            <destination>
                <groupId>0cbfb181-9bd8-34d2-0000-000000000000</groupId>
                <id>0ae476de-c16b-393e-0000-000000000000</id>
                <type>PROCESSOR</type>
            </destination>
            <flowFileExpiration>0 sec</flowFileExpiration>
            <labelIndex>1</labelIndex>
            <loadBalanceCompression>DO_NOT_COMPRESS</loadBalanceCompression>
            <loadBalancePartitionAttribute></loadBalancePartitionAttribute>
            <loadBalanceStatus>LOAD_BALANCE_NOT_CONFIGURED</loadBalanceStatus>
            <loadBalanceStrategy>DO_NOT_LOAD_BALANCE</loadBalanceStrategy>
            <name></name>
            <selectedRelationships>success</selectedRelationships>
            <source>
                <groupId>0cbfb181-9bd8-34d2-0000-000000000000</groupId>
                <id>cde22f1f-ec8b-3a35-0000-000000000000</id>
                <type>PROCESSOR</type>
            </source>
            <zIndex>0</zIndex>
        </connections>
        <connections>
            <id>f9e7cde5-7237-3b70-0000-000000000000</id>
            <parentGroupId>0cbfb181-9bd8-34d2-0000-000000000000</parentGroupId>
            <backPressureDataSizeThreshold>1 GB</backPressureDataSizeThreshold>
            <backPressureObjectThreshold>10000</backPressureObjectThreshold>
            <destination>
                <groupId>0cbfb181-9bd8-34d2-0000-000000000000</groupId>
                <id>fee7dd4b-510b-3705-0000-000000000000</id>
                <type>PROCESSOR</type>
            </destination>
            <flowFileExpiration>0 sec</flowFileExpiration>
            <labelIndex>1</labelIndex>
            <loadBalanceCompression>DO_NOT_COMPRESS</loadBalanceCompression>
            <loadBalancePartitionAttribute></loadBalancePartitionAttribute>
            <loadBalanceStatus>LOAD_BALANCE_NOT_CONFIGURED</loadBalanceStatus>
            <loadBalanceStrategy>DO_NOT_LOAD_BALANCE</loadBalanceStrategy>
            <name></name>
            <selectedRelationships>success</selectedRelationships>
            <source>
                <groupId>0cbfb181-9bd8-34d2-0000-000000000000</groupId>
                <id>7ed264f3-3912-3d41-0000-000000000000</id>
                <type>PROCESSOR</type>
            </source>
            <zIndex>0</zIndex>
        </connections>
        <controllerServices>
            <id>160fe8d9-64ac-3c0e-0000-000000000000</id>
            <parentGroupId>0cbfb181-9bd8-34d2-0000-000000000000</parentGroupId>
            <bulletinLevel>WARN</bulletinLevel>
            <bundle>
                <artifact>nifi-record-serialization-services-nar</artifact>
                <group>org.apache.nifi</group>
                <version>1.27.0</version>
            </bundle>
            <comments></comments>
            <descriptors>
                <entry>
                    <key>Schema Write Strategy</key>
                    <value>
                        <name>Schema Write Strategy</name>
                    </value>
                </entry>
                <entry>
                    <key>schema-cache</key>
                    <value>
                        <identifiesControllerService>org.apache.nifi.serialization.RecordSchemaCacheService</identifiesControllerService>
                        <name>schema-cache</name>
                    </value>
                </entry>
                <entry>
                    <key>schema-protocol-version</key>
                    <value>
                        <dependencies>
                            <dependentValues>hwx-schema-ref-attributes</dependentValues>
                            <dependentValues>hwx-content-encoded-schema</dependentValues>
                            <propertyName>Schema Write Strategy</propertyName>
                        </dependencies>
                        <name>schema-protocol-version</name>
                    </value>
                </entry>
                <entry>
                    <key>schema-access-strategy</key>
                    <value>
                        <name>schema-access-strategy</name>
                    </value>
                </entry>
                <entry>
                    <key>schema-registry</key>
                    <value>
                        <dependencies>
                            <dependentValues>confluent-encoded</dependentValues>
                            <dependentValues>schema-name</dependentValues>
                            <dependentValues>hwx-schema-ref-attributes</dependentValues>
                            <dependentValues>hwx-content-encoded-schema</dependentValues>
                            <propertyName>schema-access-strategy</propertyName>
                        </dependencies>
                        <identifiesControllerService>org.apache.nifi.schemaregistry.services.SchemaRegistry</identifiesControllerService>
                        <name>schema-registry</name>
                    </value>
                </entry>
                <entry>
                    <key>schema-name</key>
                    <value>
                        <dependencies>
                            <dependentValues>schema-name</dependentValues>
                            <propertyName>schema-access-strategy</propertyName>
                        </dependencies>
                        <name>schema-name</name>
                    </value>
                </entry>
                <entry>
                    <key>schema-version</key>
                    <value>
                        <dependencies>
                            <dependentValues>schema-name</dependentValues>
                            <propertyName>schema-access-strategy</propertyName>
                        </dependencies>
                        <name>schema-version</name>
                    </value>
                </entry>
                <entry>
                    <key>schema-branch</key>
                    <value>
                        <dependencies>
                            <dependentValues>schema-name</dependentValues>
                            <propertyName>schema-access-strategy</propertyName>
                        </dependencies>
                        <name>schema-branch</name>
                    </value>
                </entry>
                <entry>
                    <key>schema-text</key>
                    <value>
                        <dependencies>
                            <dependentValues>schema-text-property</dependentValues>
                            <propertyName>schema-access-strategy</propertyName>
                        </dependencies>
                        <name>schema-text</name>
                    </value>
                </entry>
                <entry>
                    <key>Date Format</key>
                    <value>
                        <name>Date Format</name>
                    </value>
                </entry>
                <entry>
                    <key>Time Format</key>
                    <value>
                        <name>Time Format</name>
                    </value>
                </entry>
                <entry>
                    <key>Timestamp Format</key>
                    <value>
                        <name>Timestamp Format</name>
                    </value>
                </entry>
                <entry>
                    <key>Pretty Print JSON</key>
                    <value>
                        <name>Pretty Print JSON</name>
                    </value>
                </entry>
                <entry>
                    <key>suppress-nulls</key>
                    <value>
                        <name>suppress-nulls</name>
                    </value>
                </entry>
                <entry>
                    <key>Allow Scientific Notation</key>
                    <value>
                        <name>Allow Scientific Notation</name>
                    </value>
                </entry>
                <entry>
                    <key>output-grouping</key>
                    <value>
                        <name>output-grouping</name>
                    </value>
                </entry>
                <entry>
                    <key>compression-format</key>
                    <value>
                        <name>compression-format</name>
                    </value>
                </entry>
                <entry>
                    <key>compression-level</key>
                    <value>
                        <dependencies>
                            <dependentValues>gzip</dependentValues>
                            <propertyName>compression-format</propertyName>
                        </dependencies>
                        <name>compression-level</name>
                    </value>
                </entry>
            </descriptors>
            <name>JsonRecordSetWriter</name>
            <persistsState>false</persistsState>
            <properties>
                <entry>
                    <key>Schema Write Strategy</key>
                    <value>no-schema</value>
                </entry>
                <entry>
                    <key>schema-cache</key>
                </entry>
                <entry>
                    <key>schema-protocol-version</key>
                    <value>1</value>
                </entry>
                <entry>
                    <key>schema-access-strategy</key>
                    <value>inherit-record-schema</value>
                </entry>
                <entry>
                    <key>schema-registry</key>
                </entry>
                <entry>
                    <key>schema-name</key>
                    <value>${schema.name}</value>
                </entry>
                <entry>
                    <key>schema-version</key>
                </entry>
                <entry>
                    <key>schema-branch</key>
                </entry>
                <entry>
                    <key>schema-text</key>
                    <value>${avro.schema}</value>
                </entry>
                <entry>
                    <key>Date Format</key>
                </entry>
                <entry>
                    <key>Time Format</key>
                </entry>
                <entry>
                    <key>Timestamp Format</key>
                </entry>
                <entry>
                    <key>Pretty Print JSON</key>
                    <value>false</value>
                </entry>
                <entry>
                    <key>suppress-nulls</key>
                    <value>never-suppress</value>
                </entry>
                <entry>
                    <key>Allow Scientific Notation</key>
                    <value>false</value>
                </entry>
                <entry>
                    <key>output-grouping</key>
                    <value>output-array</value>
                </entry>
                <entry>
                    <key>compression-format</key>
                    <value>none</value>
                </entry>
                <entry>
                    <key>compression-level</key>
                    <value>1</value>
                </entry>
            </properties>
            <state>ENABLED</state>
            <type>org.apache.nifi.json.JsonRecordSetWriter</type>
        </controllerServices>
        <controllerServices>
            <id>1fef5062-0310-319b-0000-000000000000</id>
            <parentGroupId>0cbfb181-9bd8-34d2-0000-000000000000</parentGroupId>
            <bulletinLevel>WARN</bulletinLevel>
            <bundle>
                <artifact>nifi-dbcp-service-nar</artifact>
                <group>org.apache.nifi</group>
                <version>1.27.0</version>
            </bundle>
            <comments></comments>
            <descriptors>
                <entry>
                    <key>Database Connection URL</key>
                    <value>
                        <name>Database Connection URL</name>
                    </value>
                </entry>
                <entry>
                    <key>Database Driver Class Name</key>
                    <value>
                        <name>Database Driver Class Name</name>
                    </value>
                </entry>
                <entry>
                    <key>database-driver-locations</key>
                    <value>
                        <name>database-driver-locations</name>
                    </value>
                </entry>
                <entry>
                    <key>kerberos-user-service</key>
                    <value>
                        <identifiesControllerService>org.apache.nifi.kerberos.KerberosUserService</identifiesControllerService>
                        <name>kerberos-user-service</name>
                    </value>
                </entry>
                <entry>
                    <key>kerberos-credentials-service</key>
                    <value>
                        <identifiesControllerService>org.apache.nifi.kerberos.KerberosCredentialsService</identifiesControllerService>
                        <name>kerberos-credentials-service</name>
                    </value>
                </entry>
                <entry>
                    <key>kerberos-principal</key>
                    <value>
                        <name>kerberos-principal</name>
                    </value>
                </entry>
                <entry>
                    <key>kerberos-password</key>
                    <value>
                        <name>kerberos-password</name>
                    </value>
                </entry>
                <entry>
                    <key>Database User</key>
                    <value>
                        <name>Database User</name>
                    </value>
                </entry>
                <entry>
                    <key>Password</key>
                    <value>
                        <name>Password</name>
                    </value>
                </entry>
                <entry>
                    <key>Max Wait Time</key>
                    <value>
                        <name>Max Wait Time</name>
                    </value>
                </entry>
                <entry>
                    <key>Max Total Connections</key>
                    <value>
                        <name>Max Total Connections</name>
                    </value>
                </entry>
                <entry>
                    <key>Validation-query</key>
                    <value>
                        <name>Validation-query</name>
                    </value>
                </entry>
                <entry>
                    <key>dbcp-min-idle-conns</key>
                    <value>
                        <name>dbcp-min-idle-conns</name>
                    </value>
                </entry>
                <entry>
                    <key>dbcp-max-idle-conns</key>
                    <value>
                        <name>dbcp-max-idle-conns</name>
                    </value>
                </entry>
                <entry>
                    <key>dbcp-max-conn-lifetime</key>
                    <value>
                        <name>dbcp-max-conn-lifetime</name>
                    </value>
                </entry>
                <entry>
                    <key>dbcp-time-between-eviction-runs</key>
                    <value>
                        <name>dbcp-time-between-eviction-runs</name>
                    </value>
                </entry>
                <entry>
                    <key>dbcp-min-evictable-idle-time</key>
                    <value>
                        <name>dbcp-min-evictable-idle-time</name>
                    </value>
                </entry>
                <entry>
                    <key>dbcp-soft-min-evictable-idle-time</key>
                    <value>
                        <name>dbcp-soft-min-evictable-idle-time</name>
                    </value>
                </entry>
            </descriptors>
            <name>DBCPConnectionPool</name>
            <persistsState>false</persistsState>
            <properties>
                <entry>
                    <key>Database Connection URL</key>
                    <value>jdbc:mysql://mysql:3306/betting_db</value>
                </entry>
                <entry>
                    <key>Database Driver Class Name</key>
                    <value>com.mysql.cj.jdbc.Driver</value>
                </entry>
                <entry>
                    <key>database-driver-locations</key>
                    <value>/opt/nifi/nifi-current/data/lib/mysql-connector-j-8.4.0.jar</value>
                </entry>
                <entry>
                    <key>kerberos-user-service</key>
                </entry>
                <entry>
                    <key>kerberos-credentials-service</key>
                </entry>
                <entry>
                    <key>kerberos-principal</key>
                </entry>
                <entry>
                    <key>kerberos-password</key>
                </entry>
                <entry>
                    <key>Database User</key>
                    <value>nifiuser</value>
                </entry>
                <entry>
                    <key>Password</key>
                </entry>
                <entry>
                    <key>Max Wait Time</key>
                    <value>500 millis</value>
                </entry>
                <entry>
                    <key>Max Total Connections</key>
                    <value>8</value>
                </entry>
                <entry>
                    <key>Validation-query</key>
                </entry>
                <entry>
                    <key>dbcp-min-idle-conns</key>
                    <value>0</value>
                </entry>
                <entry>
                    <key>dbcp-max-idle-conns</key>
                    <value>8</value>
                </entry>
                <entry>
                    <key>dbcp-max-conn-lifetime</key>
                    <value>-1</value>
                </entry>
                <entry>
                    <key>dbcp-time-between-eviction-runs</key>
                    <value>-1</value>
                </entry>
                <entry>
                    <key>dbcp-min-evictable-idle-time</key>
                    <value>30 mins</value>
                </entry>
                <entry>
                    <key>dbcp-soft-min-evictable-idle-time</key>
                    <value>-1</value>
                </entry>
            </properties>
            <state>ENABLED</state>
            <type>org.apache.nifi.dbcp.DBCPConnectionPool</type>
        </controllerServices>
        <processors>
            <id>0ae476de-c16b-393e-0000-000000000000</id>
            <parentGroupId>0cbfb181-9bd8-34d2-0000-000000000000</parentGroupId>
            <position>
                <x>792.0</x>
                <y>200.0</y>
            </position>
            <bundle>
                <artifact>nifi-standard-nar</artifact>
                <group>org.apache.nifi</group>
                <version>1.27.0</version>
            </bundle>
            <config>
                <backoffMechanism>PENALIZE_FLOWFILE</backoffMechanism>
                <bulletinLevel>WARN</bulletinLevel>
                <comments></comments>
                <concurrentlySchedulableTaskCount>1</concurrentlySchedulableTaskCount>
                <descriptors>
                    <entry>
                        <key>Log Level</key>
                        <value>
                            <name>Log Level</name>
                        </value>
                    </entry>
                    <entry>
                        <key>Log Payload</key>
                        <value>
                            <name>Log Payload</name>
                        </value>
                    </entry>
                    <entry>
                        <key>Attributes to Log</key>
                        <value>
                            <name>Attributes to Log</name>
                        </value>
                    </entry>
                    <entry>
                        <key>attributes-to-log-regex</key>
                        <value>
                            <name>attributes-to-log-regex</name>
                        </value>
                    </entry>
                    <entry>
                        <key>Attributes to Ignore</key>
                        <value>
                            <name>Attributes to Ignore</name>
                        </value>
                    </entry>
                    <entry>
                        <key>attributes-to-ignore-regex</key>
                        <value>
                            <name>attributes-to-ignore-regex</name>
                        </value>
                    </entry>
                    <entry>
                        <key>Log FlowFile Properties</key>
                        <value>
                            <name>Log FlowFile Properties</name>
                        </value>
                    </entry>
                    <entry>
                        <key>Output Format</key>
                        <value>
                            <name>Output Format</name>
                        </value>
                    </entry>
                    <entry>
                        <key>Log prefix</key>
                        <value>
                            <name>Log prefix</name>
                        </value>
                    </entry>
                    <entry>
                        <key>character-set</key>
                        <value>
                            <name>character-set</name>
                        </value>
                    </entry>
                </descriptors>
                <executionNode>ALL</executionNode>
                <lossTolerant>false</lossTolerant>
                <maxBackoffPeriod>10 mins</maxBackoffPeriod>
                <penaltyDuration>30 sec</penaltyDuration>
                <properties>
                    <entry>
                        <key>Log Level</key>
                        <value>info</value>
                    </entry>
                    <entry>
                        <key>Log Payload</key>
                        <value>false</value>
                    </entry>
                    <entry>
                        <key>Attributes to Log</key>
                    </entry>
                    <entry>
                        <key>attributes-to-log-regex</key>
                        <value>.*</value>
                    </entry>
                    <entry>
                        <key>Attributes to Ignore</key>
                    </entry>
                    <entry>
                        <key>attributes-to-ignore-regex</key>
                    </entry>
                    <entry>
                        <key>Log FlowFile Properties</key>
                        <value>true</value>
                    </entry>
                    <entry>
                        <key>Output Format</key>
                        <value>Line per Attribute</value>
                    </entry>
                    <entry>
                        <key>Log prefix</key>
                    </entry>
                    <entry>
                        <key>character-set</key>
                        <value>UTF-8</value>
                    </entry>
                </properties>
                <retryCount>10</retryCount>
                <runDurationMillis>25</runDurationMillis>
                <schedulingPeriod>0 sec</schedulingPeriod>
                <schedulingStrategy>TIMER_DRIVEN</schedulingStrategy>
                <yieldDuration>1 sec</yieldDuration>
            </config>
            <executionNodeRestricted>false</executionNodeRestricted>
            <name>LogAttribute</name>
            <relationships>
                <autoTerminate>true</autoTerminate>
                <name>success</name>
                <retry>false</retry>
            </relationships>
            <state>STOPPED</state>
            <style/>
            <type>org.apache.nifi.processors.standard.LogAttribute</type>
        </processors>
        <processors>
            <id>7ed264f3-3912-3d41-0000-000000000000</id>
            <parentGroupId>0cbfb181-9bd8-34d2-0000-000000000000</parentGroupId>
            <position>
                <x>0.0</x>
                <y>304.0</y>
            </position>
            <bundle>
                <artifact>nifi-standard-nar</artifact>
                <group>org.apache.nifi</group>
                <version>1.27.0</version>
            </bundle>
            <config>
                <backoffMechanism>PENALIZE_FLOWFILE</backoffMechanism>
                <bulletinLevel>WARN</bulletinLevel>
                <comments></comments>
                <concurrentlySchedulableTaskCount>1</concurrentlySchedulableTaskCount>
                <descriptors>
                    <entry>
                        <key>Database Connection Pooling Service</key>
                        <value>
                            <identifiesControllerService>org.apache.nifi.dbcp.DBCPService</identifiesControllerService>
                            <name>Database Connection Pooling Service</name>
                        </value>
                    </entry>
                    <entry>
                        <key>sql-pre-query</key>
                        <value>
                            <name>sql-pre-query</name>
                        </value>
                    </entry>
                    <entry>
                        <key>SQL select query</key>
                        <value>
                            <name>SQL select query</name>
                        </value>
                    </entry>
                    <entry>
                        <key>sql-post-query</key>
                        <value>
                            <name>sql-post-query</name>
                        </value>
                    </entry>
                    <entry>
                        <key>Max Wait Time</key>
                        <value>
                            <name>Max Wait Time</name>
                        </value>
                    </entry>
                    <entry>
                        <key>esqlrecord-record-writer</key>
                        <value>
                            <identifiesControllerService>org.apache.nifi.serialization.RecordSetWriterFactory</identifiesControllerService>
                            <name>esqlrecord-record-writer</name>
                        </value>
                    </entry>
                    <entry>
                        <key>esqlrecord-normalize</key>
                        <value>
                            <name>esqlrecord-normalize</name>
                        </value>
                    </entry>
                    <entry>
                        <key>dbf-user-logical-types</key>
                        <value>
                            <name>dbf-user-logical-types</name>
                        </value>
                    </entry>
                    <entry>
                        <key>dbf-default-precision</key>
                        <value>
                            <name>dbf-default-precision</name>
                        </value>
                    </entry>
                    <entry>
                        <key>dbf-default-scale</key>
                        <value>
                            <name>dbf-default-scale</name>
                        </value>
                    </entry>
                    <entry>
                        <key>esql-max-rows</key>
                        <value>
                            <name>esql-max-rows</name>
                        </value>
                    </entry>
                    <entry>
                        <key>esql-output-batch-size</key>
                        <value>
                            <name>esql-output-batch-size</name>
                        </value>
                    </entry>
                    <entry>
                        <key>esql-fetch-size</key>
                        <value>
                            <name>esql-fetch-size</name>
                        </value>
                    </entry>
                    <entry>
                        <key>esql-auto-commit</key>
                        <value>
                            <name>esql-auto-commit</name>
                        </value>
                    </entry>
                </descriptors>
                <executionNode>ALL</executionNode>
                <lossTolerant>false</lossTolerant>
                <maxBackoffPeriod>10 mins</maxBackoffPeriod>
                <penaltyDuration>30 sec</penaltyDuration>
                <properties>
                    <entry>
                        <key>Database Connection Pooling Service</key>
                        <value>1fef5062-0310-319b-0000-000000000000</value>
                    </entry>
                    <entry>
                        <key>sql-pre-query</key>
                    </entry>
                    <entry>
                        <key>SQL select query</key>
                        <value>SELECT `MONTH` FROM `report2221`</value>
                    </entry>
                    <entry>
                        <key>sql-post-query</key>
                    </entry>
                    <entry>
                        <key>Max Wait Time</key>
                        <value>0 seconds</value>
                    </entry>
                    <entry>
                        <key>esqlrecord-record-writer</key>
                        <value>160fe8d9-64ac-3c0e-0000-000000000000</value>
                    </entry>
                    <entry>
                        <key>esqlrecord-normalize</key>
                        <value>false</value>
                    </entry>
                    <entry>
                        <key>dbf-user-logical-types</key>
                        <value>false</value>
                    </entry>
                    <entry>
                        <key>dbf-default-precision</key>
                        <value>10</value>
                    </entry>
                    <entry>
                        <key>dbf-default-scale</key>
                        <value>0</value>
                    </entry>
                    <entry>
                        <key>esql-max-rows</key>
                        <value>0</value>
                    </entry>
                    <entry>
                        <key>esql-output-batch-size</key>
                        <value>0</value>
                    </entry>
                    <entry>
                        <key>esql-fetch-size</key>
                        <value>0</value>
                    </entry>
                    <entry>
                        <key>esql-auto-commit</key>
                        <value>true</value>
                    </entry>
                </properties>
                <retryCount>10</retryCount>
                <runDurationMillis>0</runDurationMillis>
                <schedulingPeriod>0 sec</schedulingPeriod>
                <schedulingStrategy>TIMER_DRIVEN</schedulingStrategy>
                <yieldDuration>1 sec</yieldDuration>
            </config>
            <executionNodeRestricted>false</executionNodeRestricted>
            <name>ExecuteSQLRecord</name>
            <relationships>
                <autoTerminate>true</autoTerminate>
                <name>failure</name>
                <retry>false</retry>
            </relationships>
            <relationships>
                <autoTerminate>false</autoTerminate>
                <name>success</name>
                <retry>false</retry>
            </relationships>
            <state>STOPPED</state>
            <style/>
            <type>org.apache.nifi.processors.standard.ExecuteSQLRecord</type>
        </processors>
        <processors>
            <id>cde22f1f-ec8b-3a35-0000-000000000000</id>
            <parentGroupId>0cbfb181-9bd8-34d2-0000-000000000000</parentGroupId>
            <position>
                <x>56.0</x>
                <y>0.0</y>
            </position>
            <bundle>
                <artifact>nifi-standard-nar</artifact>
                <group>org.apache.nifi</group>
                <version>1.27.0</version>
            </bundle>
            <config>
                <backoffMechanism>PENALIZE_FLOWFILE</backoffMechanism>
                <bulletinLevel>WARN</bulletinLevel>
                <comments></comments>
                <concurrentlySchedulableTaskCount>1</concurrentlySchedulableTaskCount>
                <descriptors>
                    <entry>
                        <key>Database Connection Pooling Service</key>
                        <value>
                            <identifiesControllerService>org.apache.nifi.dbcp.DBCPService</identifiesControllerService>
                            <name>Database Connection Pooling Service</name>
                        </value>
                    </entry>
                    <entry>
                        <key>sql-pre-query</key>
                        <value>
                            <name>sql-pre-query</name>
                        </value>
                    </entry>
                    <entry>
                        <key>SQL select query</key>
                        <value>
                            <name>SQL select query</name>
                        </value>
                    </entry>
                    <entry>
                        <key>sql-post-query</key>
                        <value>
                            <name>sql-post-query</name>
                        </value>
                    </entry>
                    <entry>
                        <key>Max Wait Time</key>
                        <value>
                            <name>Max Wait Time</name>
                        </value>
                    </entry>
                    <entry>
                        <key>dbf-normalize</key>
                        <value>
                            <name>dbf-normalize</name>
                        </value>
                    </entry>
                    <entry>
                        <key>dbf-user-logical-types</key>
                        <value>
                            <name>dbf-user-logical-types</name>
                        </value>
                    </entry>
                    <entry>
                        <key>compression-format</key>
                        <value>
                            <name>compression-format</name>
                        </value>
                    </entry>
                    <entry>
                        <key>dbf-default-precision</key>
                        <value>
                            <name>dbf-default-precision</name>
                        </value>
                    </entry>
                    <entry>
                        <key>dbf-default-scale</key>
                        <value>
                            <name>dbf-default-scale</name>
                        </value>
                    </entry>
                    <entry>
                        <key>esql-max-rows</key>
                        <value>
                            <name>esql-max-rows</name>
                        </value>
                    </entry>
                    <entry>
                        <key>esql-output-batch-size</key>
                        <value>
                            <name>esql-output-batch-size</name>
                        </value>
                    </entry>
                    <entry>
                        <key>esql-fetch-size</key>
                        <value>
                            <name>esql-fetch-size</name>
                        </value>
                    </entry>
                    <entry>
                        <key>esql-auto-commit</key>
                        <value>
                            <name>esql-auto-commit</name>
                        </value>
                    </entry>
                </descriptors>
                <executionNode>ALL</executionNode>
                <lossTolerant>false</lossTolerant>
                <maxBackoffPeriod>10 mins</maxBackoffPeriod>
                <penaltyDuration>30 sec</penaltyDuration>
                <properties>
                    <entry>
                        <key>Database Connection Pooling Service</key>
                        <value>1fef5062-0310-319b-0000-000000000000</value>
                    </entry>
                    <entry>
                        <key>sql-pre-query</key>
                    </entry>
                    <entry>
                        <key>SQL select query</key>
                        <value>SELECT `MONTH` FROM `report2221`;</value>
                    </entry>
                    <entry>
                        <key>sql-post-query</key>
                    </entry>
                    <entry>
                        <key>Max Wait Time</key>
                        <value>0 seconds</value>
                    </entry>
                    <entry>
                        <key>dbf-normalize</key>
                        <value>false</value>
                    </entry>
                    <entry>
                        <key>dbf-user-logical-types</key>
                        <value>false</value>
                    </entry>
                    <entry>
                        <key>compression-format</key>
                        <value>NONE</value>
                    </entry>
                    <entry>
                        <key>dbf-default-precision</key>
                        <value>10</value>
                    </entry>
                    <entry>
                        <key>dbf-default-scale</key>
                        <value>0</value>
                    </entry>
                    <entry>
                        <key>esql-max-rows</key>
                        <value>0</value>
                    </entry>
                    <entry>
                        <key>esql-output-batch-size</key>
                        <value>0</value>
                    </entry>
                    <entry>
                        <key>esql-fetch-size</key>
                        <value>0</value>
                    </entry>
                    <entry>
                        <key>esql-auto-commit</key>
                        <value>true</value>
                    </entry>
                </properties>
                <retryCount>10</retryCount>
                <runDurationMillis>0</runDurationMillis>
                <schedulingPeriod>0 sec</schedulingPeriod>
                <schedulingStrategy>TIMER_DRIVEN</schedulingStrategy>
                <yieldDuration>1 sec</yieldDuration>
            </config>
            <executionNodeRestricted>false</executionNodeRestricted>
            <name>ExecuteSQL</name>
            <relationships>
                <autoTerminate>true</autoTerminate>
                <name>failure</name>
                <retry>false</retry>
            </relationships>
            <relationships>
                <autoTerminate>false</autoTerminate>
                <name>success</name>
                <retry>false</retry>
            </relationships>
            <state>STOPPED</state>
            <style/>
            <type>org.apache.nifi.processors.standard.ExecuteSQL</type>
        </processors>
        <processors>
            <id>fee7dd4b-510b-3705-0000-000000000000</id>
            <parentGroupId>0cbfb181-9bd8-34d2-0000-000000000000</parentGroupId>
            <position>
                <x>576.0</x>
                <y>448.0</y>
            </position>
            <bundle>
                <artifact>nifi-standard-nar</artifact>
                <group>org.apache.nifi</group>
                <version>1.27.0</version>
            </bundle>
            <config>
                <backoffMechanism>PENALIZE_FLOWFILE</backoffMechanism>
                <bulletinLevel>WARN</bulletinLevel>
                <comments></comments>
                <concurrentlySchedulableTaskCount>1</concurrentlySchedulableTaskCount>
                <descriptors>
                    <entry>
                        <key>Database Connection Pooling Service</key>
                        <value>
                            <identifiesControllerService>org.apache.nifi.dbcp.DBCPService</identifiesControllerService>
                            <name>Database Connection Pooling Service</name>
                        </value>
                    </entry>
                    <entry>
                        <key>db-fetch-db-type</key>
                        <value>
                            <name>db-fetch-db-type</name>
                        </value>
                    </entry>
                    <entry>
                        <key>Table Name</key>
                        <value>
                            <name>Table Name</name>
                        </value>
                    </entry>
                    <entry>
                        <key>Columns to Return</key>
                        <value>
                            <name>Columns to Return</name>
                        </value>
                    </entry>
                    <entry>
                        <key>Maximum-value Columns</key>
                        <value>
                            <name>Maximum-value Columns</name>
                        </value>
                    </entry>
                    <entry>
                        <key>Max Wait Time</key>
                        <value>
                            <name>Max Wait Time</name>
                        </value>
                    </entry>
                    <entry>
                        <key>gen-table-fetch-partition-size</key>
                        <value>
                            <name>gen-table-fetch-partition-size</name>
                        </value>
                    </entry>
                    <entry>
                        <key>gen-table-column-for-val-partitioning</key>
                        <value>
                            <name>gen-table-column-for-val-partitioning</name>
                        </value>
                    </entry>
                    <entry>
                        <key>db-fetch-where-clause</key>
                        <value>
                            <name>db-fetch-where-clause</name>
                        </value>
                    </entry>
                    <entry>
                        <key>gen-table-custom-orderby-column</key>
                        <value>
                            <name>gen-table-custom-orderby-column</name>
                        </value>
                    </entry>
                    <entry>
                        <key>gen-table-output-flowfile-on-zero-results</key>
                        <value>
                            <name>gen-table-output-flowfile-on-zero-results</name>
                        </value>
                    </entry>
                </descriptors>
                <executionNode>ALL</executionNode>
                <lossTolerant>false</lossTolerant>
                <maxBackoffPeriod>10 mins</maxBackoffPeriod>
                <penaltyDuration>30 sec</penaltyDuration>
                <properties>
                    <entry>
                        <key>Database Connection Pooling Service</key>
                        <value>1fef5062-0310-319b-0000-000000000000</value>
                    </entry>
                    <entry>
                        <key>db-fetch-db-type</key>
                        <value>MySQL</value>
                    </entry>
                    <entry>
                        <key>Table Name</key>
                        <value>report2221</value>
                    </entry>
                    <entry>
                        <key>Columns to Return</key>
                        <value>`MONTH`, `YEAR`, `NEW REGISTRATIONS`, `UNIQUE DEPOSITORS`, `FTD`, `DEPOSIT TOTAL$`, `DEPOSIT TOTAL [Nº]`</value>
                    </entry>
                    <entry>
                        <key>Maximum-value Columns</key>
                    </entry>
                    <entry>
                        <key>Max Wait Time</key>
                        <value>0 seconds</value>
                    </entry>
                    <entry>
                        <key>gen-table-fetch-partition-size</key>
                        <value>10000</value>
                    </entry>
                    <entry>
                        <key>gen-table-column-for-val-partitioning</key>
                    </entry>
                    <entry>
                        <key>db-fetch-where-clause</key>
                    </entry>
                    <entry>
                        <key>gen-table-custom-orderby-column</key>
                    </entry>
                    <entry>
                        <key>gen-table-output-flowfile-on-zero-results</key>
                        <value>false</value>
                    </entry>
                </properties>
                <retryCount>10</retryCount>
                <runDurationMillis>0</runDurationMillis>
                <schedulingPeriod>0 sec</schedulingPeriod>
                <schedulingStrategy>TIMER_DRIVEN</schedulingStrategy>
                <yieldDuration>1 sec</yieldDuration>
            </config>
            <executionNodeRestricted>false</executionNodeRestricted>
            <name>GenerateTableFetch</name>
            <relationships>
                <autoTerminate>true</autoTerminate>
                <name>failure</name>
                <retry>false</retry>
            </relationships>
            <relationships>
                <autoTerminate>false</autoTerminate>
                <name>success</name>
                <retry>false</retry>
            </relationships>
            <state>STOPPED</state>
            <style/>
            <type>org.apache.nifi.processors.standard.GenerateTableFetch</type>
        </processors>
    </snippet>
    <timestamp>10/12/2024 04:09:21 UTC</timestamp>
</template>
